dllpylib/__init__.py
dllpylib/time.py
dllpylib/file.py
dllpylib-2.0.4.data/scripts/ver.py
dllpylib-2.0.4.data/scripts/lsempty.sh
dllpylib-2.0.4.data/scripts/rmempty.sh
dllpylib-2.0.4.data/scripts/retmrc.py
dllpylib-2.0.4.data/scripts/progver.py
dllpylib-2.0.4.data/scripts/keepatmost.py
dllpylib-2.0.4.data/scripts/recentf.py
dllpylib-2.0.4.data/scripts/verman.py
dllpylib-2.0.4.dist-info/top_level.txt
dllpylib-2.0.4.dist-info/METADATA
dllpylib-2.0.4.dist-info/DESCRIPTION.rst
dllpylib-2.0.4.dist-info/metadata.json
dllpylib-2.0.4.dist-info/WHEEL
dllpylib-2.0.4.dist-info/RECORD
