Metadata-Version: 2.0
Name: dllpylib
Version: 2.0.4
Summary: Yet another python library for private purposes
Home-page: https://bitbucket.org/dleonarski/dllpylib.git
Author: Dariusz Leonarski
Author-email: dariusz@leonarski.pl
License: MIT
Keywords: general,purpose,library
Platform: UNKNOWN
Classifier: Development Status :: 3 - Alpha
Classifier: Intended Audience :: Developers
Classifier: Topic :: Software Development :: Build Tools
Classifier: License :: OSI Approved :: MIT License
Classifier: Programming Language :: Python :: 3.4
Classifier: Programming Language :: Python :: 2.7
